LICENSE
MANIFEST.in
README
chiki_logger.py
setup.py
chiki_logger.egg-info/PKG-INFO
chiki_logger.egg-info/SOURCES.txt
chiki_logger.egg-info/dependency_links.txt
chiki_logger.egg-info/not-zip-safe
chiki_logger.egg-info/requires.txt
chiki_logger.egg-info/top_level.txt