Metadata-Version: 1.0
Name: chiki-logger
Version: 0.0.1
Summary: chiki logger libs.
Home-page: https://github.com/endsh/chiki-logger
Author: Linshao
Author-email: 438985635@qq.com
License: UNKNOWN
Platform: any
